geopyspread/__init__.py
geopyspread/common.py
geopyspread/geopyspread.py
geopyspread-0.0.1.dist-info/LICENSE
geopyspread-0.0.1.dist-info/METADATA
geopyspread-0.0.1.dist-info/WHEEL
geopyspread-0.0.1.dist-info/entry_points.txt
geopyspread-0.0.1.dist-info/top_level.txt
geopyspread-0.0.1.dist-info/RECORD
